[
  {
    "id": 13001388,
    "type": "SOA",
    "name": "@",
    "data": "1800",
    "priority": 0,
    "port": 0,
    "ttl": 1800,
    "weight": 0,
    "flags": 0
  },
  {
    "id": 13001389,
    "type": "NS",
    "name": "@",
    "data": "ns1.digitalocean.com",
    "priority": 0,
    "port": 0,
    "ttl": 1800,
    "weight": 0,
    "flags": 0
  },
  {
    "id": 13001390,
    "type": "NS",
    "name": "@",
    "data": "ns2.digitalocean.com",
    "priority": 0,
    "port": 0,
    "ttl": 1800,
    "weight": 0,
    "flags": 0
  },
  {
    "id": 13001391,
    "type": "NS",
    "name": "@",
    "data": "ns3.digitalocean.com",
    "priority": 0,
    "port": 0,
    "ttl": 1800,
    "weight": 0,
    "flags": 0
  },
  {
    "id": 13001392,
    "type": "A",
    "name": "@",
    "data": "174.138.101.139",
    "priority": 0,
    "port": 0,
    "ttl": 300,
    "weight": 0,
    "flags": 0
  },
  {
    "id": 20247781,
    "type": "MX",
    "name": "@",
    "data": "mail.visualcu.es",
    "priority": 50,
    "port": 0,
    "ttl": 1800,
    "weight": 0,
    "flags": 0
  },
  {
    "id": 99383864,
    "type": "CNAME",
    "name": "blog",
    "data": "@",
    "priority": 0,
    "port": 0,
    "ttl": 300,
    "weight": 0,
    "flags": 0
  },
  {
    "id": 99383867,
    "type": "CNAME",
    "name": "app",
    "data": "@",
    "priority": 0,
    "port": 0,
    "ttl": 300,
    "weight": 0,
    "flags": 0
  },
  {
    "id": 99383869,
    "type": "CNAME",
    "name": "git",
    "data": "@",
    "priority": 0,
    "port": 0,
    "ttl": 300,
    "weight": 0,
    "flags": 0
  },
  {
    "id": 99383878,
    "type": "CNAME",
    "name": "mail",
    "data": "@",
    "priority": 0,
    "port": 0,
    "ttl": 300,
    "weight": 0,
    "flags": 0
  },
  {
    "id": 102027103,
    "type": "CNAME",
    "name": "data",
    "data": "@",
    "priority": 0,
    "port": 0,
    "ttl": 300,
    "weight": 0,
    "flags": 0
  },
  {
    "id": 102027104,
    "type": "CNAME",
    "name": "api",
    "data": "@",
    "priority": 0,
    "port": 0,
    "ttl": 300,
    "weight": 0,
    "flags": 0
  },
  {
    "id": 102027116,
    "type": "CNAME",
    "name": "static",
    "data": "@",
    "priority": 0,
    "port": 0,
    "ttl": 300,
    "weight": 0,
    "flags": 0
  },
  {
    "id": 102027136,
    "type": "CNAME",
    "name": "files",
    "data": "@",
    "priority": 0,
    "port": 0,
    "ttl": 300,
    "weight": 0,
    "flags": 0
  },
  {
    "id": 113034106,
    "type": "CNAME",
    "name": "splash",
    "data": "@",
    "priority": 0,
    "port": 0,
    "ttl": 300,
    "weight": 0,
    "flags": 0
  },
  {
    "id": 266504273,
    "type": "A",
    "name": "@",
    "data": "174.138.101.139",
    "priority": 0,
    "port": 0,
    "ttl": 300,
    "weight": 0,
    "flags": 0
  },
  {
    "id": 266514332,
    "type": "A",
    "name": "@",
    "data": "174.138.101.139",
    "priority": 0,
    "port": 0,
    "ttl": 300,
    "weight": 0,
    "flags": 0
  }
]